<?xml version="1.0" encoding="utf-8"?><sys><loid>3.0.1211500373</loid><uuid>dc3b3c48-0281-11e8-8ba7-cdc29d688b6b</uuid><path>/Production/LesEchos/Articles/PME Regions/Innovateurs/INNOV Poietis.xml</path><name>INNOV Poietis.xml</name><description/><type>EOM::CompoundStory</type><owner>chouzelle</owner><creator>chouzelle</creator><timeCreated>1516961740</timeCreated><lastModifier>chouzelle</lastModifier><timeModified>1517418167</timeModified><locker/><timeLocked>1517418167</timeLocked><statusName>LE-Articles-Redaction/Mise en ligne</statusName><statusIdentifier>RGB(243,2,252)</statusIdentifier><size>4769</size><updateCounter>404</updateCounter><props>	<workFolder>/Redaction/PME-REGIONS/Innovateurs</workFolder>	<productInfo>		<name>LEC-Redaction</name>		<issueDate>20180131</issueDate>	</productInfo>	<templateName>/SysConfig/LesEchos/HorsPage/Templates/Article_swing.xml</templateName>	<process>		<type>spelling</type>		<user>chouzelle</user>	</process>	<edSection>PME &amp; Regions</edSection>				<summary>Frank Niedercorn @FNiedercorn Fabriqué par bio-impression 3D, Poieskin est un modèle de peau totale humaine, très proche d&apos;un tissu natif avec sa structure faite de compartiments dermiques et épidermiques. Poietis A peine un demi-millimètre d&apos;épa</summary><charsCount>2937</charsCount><wordCount>446</wordCount><createdDate>20180126101540</createdDate></props><tl><t><id>2</id><tp>ExternalFileProxy</tp><c>chouzelle</c><cd>20180126101500</cd><dt><ip>10.70.51.179</ip><ts>1516961796182</ts><applicationId>Swing</applicationId></dt></t><t><id>30</id><tp>PrintLink</tp><c>smeunier</c><cd>20180131175000</cd><dt><uid lid="U301230931445nuH" path="PME2 0102.pgl">2c04f244-0667-11e8-bf19-1dbe003e5157</uid><channel>LEC-Journal</channel><issueDate>20180201</issueDate><size>2150c/35L50</size><story><name>ArticleA</name><type>Article Innovateurs</type></story></dt></t><t><id>31</id><tp>Export</tp><c>chouzelle</c><cd>20180131170200</cd><dt><channel>LEC-Redaction</channel><last>20180131180245</last></dt></t><t><id>32</id><tp>EOM::Status</tp><c>chouzelle</c><cd>20180131170200</cd><dt><status comment="Photo envoyée par mail"/></dt></t><t><id>34</id><tp>EOM::Task</tp><c>chouzelle</c><cd>20180131170200</cd><dt><task comment="Photo envoyée par mail" creator="chouzelle" priority="0" status="0" subject="INNOV Poietis" uuid="cd71adaa-0281-11e8-8ba7-cdc29d688b6b"/></dt></t></tl><va xmlns:eom="http://www.eidosmedia.com/eom"><folder_size>1</folder_size><parent_uuid>2f524cee-2deb-11e2-b509-00144f465cc6</parent_uuid><oteam>Service_REGIONS-COLLECTIVITES</oteam><cteam>Service_REGIONS-COLLECTIVITES</cteam><vid>11</vid><vt>1517418159</vt></va></sys>